odoo/addons/base_revision/README.rst
odoo/addons/base_revision/__init__.py
odoo/addons/base_revision/__manifest__.py
odoo/addons/base_revision/i18n/base_revision.pot
odoo/addons/base_revision/i18n/es.po
odoo/addons/base_revision/i18n/hr.po
odoo/addons/base_revision/i18n/it.po
odoo/addons/base_revision/models/__init__.py
odoo/addons/base_revision/models/base_revision.py
odoo/addons/base_revision/readme/CONTRIBUTORS.rst
odoo/addons/base_revision/readme/DESCRIPTION.rst
odoo/addons/base_revision/static/description/icon.png
odoo/addons/base_revision/static/description/index.html
odoo/addons/base_revision/tests/__init__.py
odoo/addons/base_revision/tests/base_revision_tester.py
odoo/addons/base_revision/tests/test_base_revision.py
odoo14_addon_base_revision-14.0.1.1.1.dist-info/METADATA
odoo14_addon_base_revision-14.0.1.1.1.dist-info/WHEEL
odoo14_addon_base_revision-14.0.1.1.1.dist-info/top_level.txt
odoo14_addon_base_revision-14.0.1.1.1.dist-info/RECORD
